ghj_pkg/__init__.py
ghj_pkg/nn/__init__.py
ghj_pkg/nn/core.py
ghj_pkg/utlis/__init__.py
ghj_pkg/utlis/utilities.py
ghj_pkg-0.0.1.dist-info/LICENSE
ghj_pkg-0.0.1.dist-info/METADATA
ghj_pkg-0.0.1.dist-info/WHEEL
ghj_pkg-0.0.1.dist-info/top_level.txt
ghj_pkg-0.0.1.dist-info/RECORD
