Metadata-Version: 2.1
Name: ghj-pkg
Version: 0.0.1
Summary: This is a mini but function completed neural networks framework
Home-page: https://github.com/ghj-hey
Author: Haojie Guo
Author-email: ghj_xin@163.com
License: UNKNOWN
Platform: UNKNOWN
Classifier: Programming Language :: Python :: 3
Classifier: License :: OSI Approved :: MIT License
Classifier: Operating System :: OS Independent
Requires-Python: >=3.6
